steputils/__init__.py
steputils/exceptions.py
steputils/p21.py
steputils/strings.py
steputils/tools.py
steputils/version.py
steputils/express/__init__.py
steputils/express/ast.py
steputils/express/expressLexer.py
steputils/express/expressListener.py
steputils/express/expressParser.py
steputils/express/parser.py
steputils/express/pyparser.py
steputils-0.1.dist-info/LICENSE.txt
steputils-0.1.dist-info/METADATA
steputils-0.1.dist-info/WHEEL
steputils-0.1.dist-info/top_level.txt
steputils-0.1.dist-info/RECORD
