Metadata-Version: 2.1
Name: steputils
Version: 0.1
Summary: A Python package to read/write STEP data files.
Home-page: http://github.com/mozman/steputils
Download-URL: https://pypi.org/project/steputils/
Author: Manfred Moitzi
Author-email: me@mozman.at
License: MIT License
Project-URL: Documentation, https://steputils.readthedocs.io
Project-URL: Wiki, https://github.com/mozman/steputils/wiki
Project-URL: Source, http://github.com/mozman/steputils
Project-URL: Bug Tracker, https://github.com/mozman/steputils/issues
Keywords: IFC4,CAD,STEP
Platform: OS Independent
Classifier: Development Status :: 2 - Pre-Alpha
Classifier: License :: OSI Approved :: MIT License
Classifier: Operating System :: OS Independent
Classifier: Programming Language :: Python :: 3
Classifier: Programming Language :: Python :: 3.7
Classifier: Programming Language :: Python :: 3.8
Classifier: Programming Language :: Python :: 3.9
Classifier: Programming Language :: Python :: 3.10
Classifier: Programming Language :: Python :: Implementation :: CPython
Classifier: Programming Language :: Python :: Implementation :: PyPy
Classifier: Intended Audience :: Developers
Classifier: Topic :: Software Development :: Libraries :: Python Modules
Provides: steputils
Requires-Python: >=3.7
License-File: LICENSE.txt
